sxth_mind/__init__.py
sxth_mind/mind.py
sxth_mind/adapters/__init__.py
sxth_mind/adapters/base.py
sxth_mind/api/__init__.py
sxth_mind/api/app.py
sxth_mind/api/routes.py
sxth_mind/cli/__init__.py
sxth_mind/cli/main.py
sxth_mind/engine/__init__.py
sxth_mind/engine/nudge_engine.py
sxth_mind/providers/__init__.py
sxth_mind/providers/base.py
sxth_mind/providers/openai.py
sxth_mind/schemas/__init__.py
sxth_mind/schemas/insight.py
sxth_mind/schemas/memory.py
sxth_mind/schemas/nudge.py
sxth_mind/schemas/project_mind.py
sxth_mind/schemas/user_mind.py
sxth_mind/storage/__init__.py
sxth_mind/storage/base.py
sxth_mind/storage/memory.py
sxth_mind/storage/sqlite.py
sxth_mind-0.1.0.dist-info/METADATA
sxth_mind-0.1.0.dist-info/WHEEL
sxth_mind-0.1.0.dist-info/entry_points.txt
sxth_mind-0.1.0.dist-info/licenses/LICENSE
sxth_mind-0.1.0.dist-info/RECORD
