Metadata-Version: 2.4
Name: sxth-mind
Version: 0.1.0
Summary: The understanding layer for adaptive AI products
Project-URL: Homepage, https://github.com/sxth-ai/sxth-mind
Project-URL: Documentation, https://docs.sxth.ai
Project-URL: Repository, https://github.com/sxth-ai/sxth-mind
Project-URL: Issues, https://github.com/sxth-ai/sxth-mind/issues
Author-email: "sxth.ai" <hello@sxth.ai>
License-Expression: MIT
License-File: LICENSE
Keywords: agents,ai,cognitive-state,llm,memory,personalization
Classifier: Development Status :: 3 - Alpha
Classifier: Intended Audience :: Developers
Classifier: License :: OSI Approved :: MIT License
Classifier: Programming Language :: Python :: 3
Classifier: Programming Language :: Python :: 3.11
Classifier: Programming Language :: Python :: 3.12
Classifier: Topic :: Scientific/Engineering :: Artificial Intelligence
Requires-Python: >=3.10
Requires-Dist: pydantic>=2.0
Provides-Extra: agno
Requires-Dist: agno>=1.0; extra == 'agno'
Provides-Extra: all
Requires-Dist: agno>=1.0; extra == 'all'
Requires-Dist: aiosqlite>=0.19; extra == 'all'
Requires-Dist: asyncpg>=0.29; extra == 'all'
Requires-Dist: fastapi>=0.100; extra == 'all'
Requires-Dist: httpx>=0.25; extra == 'all'
Requires-Dist: mypy>=1.0; extra == 'all'
Requires-Dist: pytest-asyncio>=0.21; extra == 'all'
Requires-Dist: pytest>=7.0; extra == 'all'
Requires-Dist: ruff>=0.1; extra == 'all'
Requires-Dist: sqlalchemy>=2.0; extra == 'all'
Requires-Dist: uvicorn>=0.23; extra == 'all'
Provides-Extra: api
Requires-Dist: fastapi>=0.100; extra == 'api'
Requires-Dist: httpx>=0.25; extra == 'api'
Requires-Dist: uvicorn>=0.23; extra == 'api'
Provides-Extra: dev
Requires-Dist: mypy>=1.0; extra == 'dev'
Requires-Dist: pytest-asyncio>=0.21; extra == 'dev'
Requires-Dist: pytest>=7.0; extra == 'dev'
Requires-Dist: ruff>=0.1; extra == 'dev'
Provides-Extra: openai
Requires-Dist: openai>=1.0; extra == 'openai'
Provides-Extra: postgres
Requires-Dist: asyncpg>=0.29; extra == 'postgres'
Requires-Dist: sqlalchemy>=2.0; extra == 'postgres'
Provides-Extra: sqlite
Requires-Dist: aiosqlite>=0.19; extra == 'sqlite'
